README.md
setup.cfg
setup.py
pymuller/__init__.py
pymuller/logic.py
pymuller.egg-info/PKG-INFO
pymuller.egg-info/SOURCES.txt
pymuller.egg-info/dependency_links.txt
pymuller.egg-info/not-zip-safe
pymuller.egg-info/requires.txt
pymuller.egg-info/top_level.txt