Metadata-Version: 1.0
Name: pymuller
Version: 0.1.1
Summary: Muller plot generation in Python
Home-page: UNKNOWN
Author: UNKNOWN
Author-email: boaz85@gmail.com
License: UNKNOWN
Platform: UNKNOWN
